LICENSE
MANIFEST.in
README.md
setup.cfg
setup.py
syncthingmanager/__init__.py
syncthingmanager/conftest.py
syncthingmanager.egg-info/PKG-INFO
syncthingmanager.egg-info/SOURCES.txt
syncthingmanager.egg-info/dependency_links.txt
syncthingmanager.egg-info/entry_points.txt
syncthingmanager.egg-info/requires.txt
syncthingmanager.egg-info/top_level.txt