Metadata-Version: 1.1
Name: syncthingmanager
Version: 0.1.0
Summary: A commandline tool for configuring Syncthing
Home-page: https://github.com/classicsc/syncthingmanager
Author: Samuel Smoker
Author-email: smoker@usc.edu
License: GPLv3
Keywords: syncthing
Platform: UNKNOWN
Classifier: Development Status :: 3 - Alpha
Classifier: Intended Audience :: End Users/Desktop
Classifier: Intended Audience :: System Administrators
Classifier: Topic :: System :: Archiving :: Mirroring
Classifier: Topic :: Utilities
Classifier: Natural Language :: English
Classifier: License :: OSI Approved :: GNU General Public License v3 (GPLv3)
Classifier: Programming Language :: Python :: 3.4
